[
    [{
        "id": 0,
        "name": "追加ボタン用",
        "description": "初期表示時の追加ボタン用データ"
    }, {
        "id": 1,
        "name": "A",
        "description": "C"
    }, {
        "id": 2,
        "name": "どうぶつの名前",
        "description": "動物の名前を集めた辞書"
    }],
    [{
        "dictId": 1,
        "words": [{
            "id": 1,
            "word": "A",
            "yomi": "B",
            "description": "C"
        }, {
            "id": 1,
            "word": "W",
            "yomi": "S",
            "description": "X"
        }]
    }, {
        "dictId": 2,
        "words": [{
            "id": 1,
            "word": "きりん",
            "yomi": "きりん",
            "description": "首の長い動物"
        }]
    }]
]
